pyliger-0.2.4.dist-info/METADATA
pyliger-0.2.4.dist-info/WHEEL
pyliger-0.2.4.dist-info/entry_points.txt
pyliger-0.2.4.dist-info/licenses/LICENSE
pyliger/__init__.py
pyliger/_utilities.py
pyliger/clustering/_leiden.py
pyliger/clustering/_louvain.py
pyliger/clustering/_utilities.py
pyliger/clustering/todo.py
pyliger/datasets/PBMC_control.h5ad
pyliger/datasets/PBMC_interferon-stimulated.h5ad
pyliger/datasets/pbmc_ctrl.h5ad
pyliger/datasets/pbmc_stim.h5ad
pyliger/factorization/_iNMF_ANLS.py
pyliger/factorization/_iNMF_HALS.py
pyliger/factorization/_online_iNMF.py
pyliger/factorization/_utilities.py
pyliger/factorization/todo.py
pyliger/logging.py
pyliger/plotting/_dataset_cluster.py
pyliger/plotting/_gene.py
pyliger/plotting/_gene_loadings.py
pyliger/plotting/_go.py
pyliger/plotting/_spatial.py
pyliger/plotting/_utilities.py
pyliger/plotting/todo.py
pyliger/preprocessing/_cal_feature.py
pyliger/preprocessing/_initialization.py
pyliger/preprocessing/_normalization.py
pyliger/preprocessing/_qc.py
pyliger/preprocessing/_scale.py
pyliger/preprocessing/_select_genes.py
pyliger/pyliger.py
pyliger/read_write.py
pyliger/tools/_go.py
pyliger/tools/_marker.py
pyliger/tools/_metrics.py
pyliger/tools/_quantile_norm.py
pyliger/tools/_umap.py
pyliger/tools/_wilcoxon.py
pyliger/tools/todo.py
pyliger-0.2.4.dist-info/RECORD
